pyqtorch/__init__.py
pyqtorch/api.py
pyqtorch/apply.py
pyqtorch/circuit.py
pyqtorch/embed.py
pyqtorch/matrices.py
pyqtorch/py.typed
pyqtorch/quantum_operation.py
pyqtorch/qubit_support.py
pyqtorch/utils.py
pyqtorch/utils_distributions.py
pyqtorch/composite/__init__.py
pyqtorch/composite/compose.py
pyqtorch/composite/sequence.py
pyqtorch/differentiation/__init__.py
pyqtorch/differentiation/adjoint.py
pyqtorch/differentiation/gpsr.py
pyqtorch/hamiltonians/__init__.py
pyqtorch/hamiltonians/evolution.py
pyqtorch/hamiltonians/observable.py
pyqtorch/noise/__init__.py
pyqtorch/noise/analog.py
pyqtorch/noise/digital_gates.py
pyqtorch/noise/digital_protocol.py
pyqtorch/noise/readout.py
pyqtorch/primitives/__init__.py
pyqtorch/primitives/mutation_utils.py
pyqtorch/primitives/parametric.py
pyqtorch/primitives/parametric_gates.py
pyqtorch/primitives/primitive.py
pyqtorch/primitives/primitive_gates.py
pyqtorch/time_dependent/README
pyqtorch/time_dependent/__init__.py
pyqtorch/time_dependent/mesolve.py
pyqtorch/time_dependent/options.py
pyqtorch/time_dependent/sesolve.py
pyqtorch/time_dependent/solvers.py
pyqtorch/time_dependent/integrators/__init__.py
pyqtorch/time_dependent/integrators/adaptive.py
pyqtorch/time_dependent/integrators/krylov.py
pyqtorch/time_dependent/methods/__init__.py
pyqtorch/time_dependent/methods/dp5.py
pyqtorch/time_dependent/methods/krylov.py
pyqtorch-1.7.8.dist-info/METADATA
pyqtorch-1.7.8.dist-info/WHEEL
pyqtorch-1.7.8.dist-info/licenses/LICENSE
pyqtorch-1.7.8.dist-info/RECORD
