Metadata-Version: 2.4
Name: pyqtorch
Version: 1.7.8
Summary: An efficient, large-scale emulator designed for quantum machine learning, seamlessly integrated with a PyTorch backend. Please refer to https://pyqtorch.readthedocs.io/en/latest/ for setup and usage info, along with the full documentation.
Project-URL: Documentation, https://pasqal-io.github.io/pyqtorch/latest/
Project-URL: Issues, https://github.com/pasqal-io/pyqtorch/-/issues
Project-URL: Source, https://github.com/pasqal-io/pyqtorch
Author-email: Slimane Thabet <slimane.thabet@pasqal.com>, Aleksander Wennersteen <aleksander.wennersteen@pasqal.com>, Mario Dagrada <mario.dagrada@pasqal.com>, Dominik Seitz <dominik.seitz@pasqal.com>, Niklas Heim <niklas.heim@pasqal.com>, Roland Guichard <roland.guichard@pasqal.com>, "Joao P. Moutinho" <joao.moutinho@pasqal.com>, Vytautas Abramavicius <vytautas.abramavicius@pasqal.com>, Anton Quelle <anton.quelle@pasqal.com>, Charles Moussa <charles.moussa@pasqal.com>, Callum Duffy <callum.duff
License: Apache 2.0
License-File: LICENSE
Keywords: quantum
Classifier: License :: OSI Approved :: Apache Software License
Classifier: Programming Language :: Python
Classifier: Programming Language :: Python :: 3
Classifier: Programming Language :: Python :: 3.8
Classifier: Programming Language :: Python :: 3.9
Classifier: Programming Language :: Python :: 3.10
Classifier: Programming Language :: Python :: 3.11
Classifier: Programming Language :: Python :: 3.12
Classifier: Programming Language :: Python :: Implementation :: CPython
Classifier: Programming Language :: Python :: Implementation :: PyPy
Requires-Python: >=3.9
Requires-Dist: numpy
Requires-Dist: torch
Provides-Extra: dev
Requires-Dist: black; extra == 'dev'
Requires-Dist: flake8; extra == 'dev'
Requires-Dist: flaky; extra == 'dev'
Requires-Dist: matplotlib; extra == 'dev'
Requires-Dist: mypy; extra == 'dev'
Requires-Dist: pre-commit; extra == 'dev'
Requires-Dist: pytest; extra == 'dev'
Requires-Dist: pytest-cov; extra == 'dev'
Requires-Dist: pytest-xdist; extra == 'dev'
Requires-Dist: ruff; extra == 'dev'
Provides-Extra: testlibs
Requires-Dist: jax; extra == 'testlibs'
Requires-Dist: jaxlib; extra == 'testlibs'
Requires-Dist: qutip; extra == 'testlibs'
